trustloop/__init__.py
trustloop/api.py
trustloop/data.py
trustloop/domains.py
trustloop/eventbus.py
trustloop-0.1.0.dist-info/METADATA
trustloop-0.1.0.dist-info/WHEEL
trustloop-0.1.0.dist-info/top_level.txt
trustloop-0.1.0.dist-info/RECORD
