Metadata-Version: 2.4
Name: trustloop
Version: 0.1.0
Summary: TrustLoop Python client for interacting with TrustLoop servers
Author-email: TrustLoop <hello@trustloop.com>
License: MIT
Project-URL: Homepage, https://github.com/trustloop/trustloop-python
Project-URL: Repository, https://github.com/trustloop/trustloop-python
Project-URL: Documentation, https://docs.trustloop.com
Project-URL: Bug Tracker, https://github.com/trustloop/trustloop-python/issues
Keywords: trustloop,api,client,data,domains
Classifier: Development Status :: 3 - Alpha
Classifier: Intended Audience :: Developers
Classifier: License :: OSI Approved :: MIT License
Classifier: Programming Language :: Python :: 3
Classifier: Programming Language :: Python :: 3.8
Classifier: Programming Language :: Python :: 3.9
Classifier: Programming Language :: Python :: 3.10
Classifier: Programming Language :: Python :: 3.11
Classifier: Programming Language :: Python :: 3.12
Requires-Python: >=3.8
Provides-Extra: dev
Requires-Dist: pytest>=7.0; extra == "dev"
Requires-Dist: black>=22.0; extra == "dev"
Requires-Dist: isort>=5.0; extra == "dev"
Requires-Dist: flake8>=4.0; extra == "dev"
Requires-Dist: build>=0.8.0; extra == "dev"
Requires-Dist: twine>=4.0.0; extra == "dev"
